aiomysql/__init__.py
aiomysql/connection.py
aiomysql/cursors.py
aiomysql/log.py
aiomysql/pool.py
aiomysql/utils.py
aiomysql/sa/__init__.py
aiomysql/sa/connection.py
aiomysql/sa/engine.py
aiomysql/sa/exc.py
aiomysql/sa/result.py
aiomysql/sa/transaction.py
privex_aiomysql-0.0.21.dist-info/LICENSE
privex_aiomysql-0.0.21.dist-info/METADATA
privex_aiomysql-0.0.21.dist-info/WHEEL
privex_aiomysql-0.0.21.dist-info/top_level.txt
privex_aiomysql-0.0.21.dist-info/RECORD
